README.rst
setup.py
dk_car_scraper/__init__.py
dk_car_scraper/scraper.py
dk_car_scraper.egg-info/PKG-INFO
dk_car_scraper.egg-info/SOURCES.txt
dk_car_scraper.egg-info/dependency_links.txt
dk_car_scraper.egg-info/requires.txt
dk_car_scraper.egg-info/top_level.txt
tests/__init__.py
tests/tests.py