Metadata-Version: 1.1
Name: dk-car-scraper
Version: 1.0.5
Summary: A python module which returns details about a Danish car from its license plate number
Home-page: https://github.com/joshuakarjala/dk-car-scraper/
Author: Joshua Karjala-Svenden
Author-email: joshua@fluxuries.com
License: MIT
Platform: any
Classifier: Development Status :: 5 - Production/Stable
Classifier: Intended Audience :: Developers
Classifier: License :: OSI Approved :: MIT License
Classifier: Operating System :: OS Independent
Classifier: Programming Language :: Python
Classifier: Topic :: Software Development :: Libraries :: Python Modules
